pyomarker/__init__.py
pyomarker/_core/__init__.py
pyomarker/_core/engine.py
pyomarker/_utilities/__init__.py
pyomarker/_utilities/coordinate_conversions.py
pyomarker/_utilities/dirichlet_mixture.py
pyomarker/models/__init__.py
pyomarker/models/mixture/__init__.py
pyomarker/models/mixture/habitat_fixed_baseline_model.py
pyomarker/models/mixture/mixture_model.py
pyomarker/models/mixture/real_mixture.py
pyomarker/models/mixture/stan/dirichlet_multinomial_fixed_baseline.stan
pyomarker/models/test_object/__init__.py
pyomarker/models/test_object/real/__init__.py
pyomarker/models/test_object/real/mixture/__init__.py
pyomarker/models/test_retest/__init__.py
pyomarker/models/test_retest/real/__init__.py
pyomarker/models/test_retest/real/bland_altman.py
pyomarker/models/test_retest/real/mixture/__init__.py
pyomarker-0.0.1.dev15.dist-info/METADATA
pyomarker-0.0.1.dev15.dist-info/WHEEL
pyomarker-0.0.1.dev15.dist-info/licenses/LICENSE.md
pyomarker-0.0.1.dev15.dist-info/RECORD
