Metadata-Version: 2.4
Name: pyomarker
Version: 0.0.1.dev15
Summary: A library of tools and functionality for frequentist and Bayesian imaging biomarker analysis.
Project-URL: Homepage, https://github.com/ICR-Computational-Imaging/pyomarker
Project-URL: Issues, https://github.com/ICR-Computational-Imaging/pyomarker/issues
Author-email: Matthew D Blackledge <matthew.blackledge@icr.ac.uk>
Maintainer-email: Matthew D Blackledge <matthew.blackledge@icr.ac.uk>
License:                                  Apache License
License-File: LICENSE.md
Keywords: Bayesian Modelling,Biomarkers,Image Processing,Medical Imaging
Classifier: License :: OSI Approved :: Apache Software License
Classifier: Natural Language :: English
Classifier: Programming Language :: Python :: 3
Requires-Python: >=3.8
Requires-Dist: arviz
Requires-Dist: bump2version
Requires-Dist: cmdstanpy
Requires-Dist: mkdocs
Requires-Dist: numpy
Requires-Dist: pylint
Requires-Dist: pytest
Requires-Dist: scipy
Requires-Dist: tqdm
Provides-Extra: test
Requires-Dist: pytest-cov; extra == 'test'
Requires-Dist: pytest-html; extra == 'test'
Requires-Dist: pytest>=8; extra == 'test'
